{
  "url": "https://headlesscommercesummit.com/",
  "requestedUrl": "https://headlesscommercesummit.com/",
  "timestamp": 1624854104419,
  "ranks": {
    "hundos": 17,
    "performance": 17,
    "accessibility": 15,
    "cumulative": 17
  },
  "lighthouse": {
    "version": "7.5.0",
    "performance": 0.46,
    "accessibility": 0.97,
    "bestPractices": 1,
    "seo": 1,
    "total": 343
  },
  "firstContentfulPaint": 2148.0019999999995,
  "speedIndex": 5074.806800950722,
  "largestContentfulPaint": 3888.0514999999996,
  "totalBlockingTime": 1474.9209999999994,
  "cumulativeLayoutShift": 0.0012224934895833331,
  "timeToInteractive": 12013.129,
  "maxPotentialFirstInputDelay": 370,
  "timeToFirstByte": 292.304,
  "weight": {
    "summary": "64 requests • 1,287 KiB",
    "total": 1317632,
    "image": 156798,
    "imageCount": 29,
    "script": 933485,
    "scriptCount": 19,
    "document": 43395,
    "font": 135374,
    "fontCount": 6,
    "stylesheet": 47037,
    "stylesheetCount": 2,
    "thirdParty": 1124178,
    "thirdPartyCount": 52
  },
  "run": {
    "number": 3,
    "total": 3
  },
  "axe": {
    "passes": 1009,
    "violations": 30
  }
}