{
  "url": "https://www.pantip.com/",
  "requestedUrl": "https://www.pantip.com/",
  "timestamp": 1651596158447,
  "ranks": {
    "hundos": 3,
    "performance": 6,
    "accessibility": 5,
    "cumulative": 3
  },
  "lighthouse": {
    "version": "9.5.0",
    "performance": 0.2,
    "accessibility": 0.73,
    "bestPractices": 0.92,
    "seo": 0.85,
    "total": 270
  },
  "firstContentfulPaint": 3099.5779999999995,
  "firstMeaningfulPaint": 3099.5779999999995,
  "speedIndex": 14646.799739540711,
  "largestContentfulPaint": 12565.459999999997,
  "totalBlockingTime": 994.9999999999964,
  "cumulativeLayoutShift": 0.270625,
  "timeToInteractive": 15609.274999999996,
  "maxPotentialFirstInputDelay": 1064.9999999999982,
  "timeToFirstByte": 2902.0950000000003,
  "weight": {
    "summary": "130 requests • 2,337 KiB",
    "total": 2393289,
    "image": 821026,
    "imageCount": 66,
    "script": 1378283,
    "scriptCount": 19,
    "document": 21074,
    "font": 44615,
    "fontCount": 1,
    "stylesheet": 78510,
    "stylesheetCount": 2,
    "thirdParty": 840056,
    "thirdPartyCount": 59
  },
  "run": {
    "number": 1,
    "total": 3
  },
  "axe": {
    "passes": 2197,
    "violations": 561
  }
}