{
  "url": "https://jamstack.org/",
  "requestedUrl": "https://jamstack.org/",
  "timestamp": 1636259149658,
  "ranks": {
    "hundos": 17,
    "performance": 17,
    "accessibility": 13,
    "cumulative": 17
  },
  "lighthouse": {
    "version": "6.5.0",
    "performance": null,
    "accessibility": 0.98,
    "bestPractices": 1,
    "seo": 1,
    "total": 298
  },
  "firstContentfulPaint": 1105.2980000000002,
  "speedIndex": 1105.2980000000002,
  "totalBlockingTime": 73.5,
  "cumulativeLayoutShift": 0.8515625,
  "timeToInteractive": 1997.5860000000002,
  "maxPotentialFirstInputDelay": 170,
  "timeToFirstByte": 3.8640000000000043,
  "weight": {
    "summary": "10 requests • 153 KiB",
    "total": 157147,
    "image": 101688,
    "imageCount": 4,
    "script": 22740,
    "scriptCount": 2,
    "document": 22729,
    "font": 0,
    "fontCount": 0,
    "stylesheet": 9345,
    "stylesheetCount": 1,
    "thirdParty": 125073,
    "thirdPartyCount": 8
  },
  "axe": {
    "passes": 635,
    "violations": 25
  }
}