{
  "url": "https://www.dek-d.com/",
  "requestedUrl": "https://www.dek-d.com/",
  "timestamp": 1642264875492,
  "ranks": {
    "hundos": 7,
    "performance": 6,
    "accessibility": 7,
    "cumulative": 7
  },
  "lighthouse": {
    "version": "6.5.0",
    "performance": 0.07,
    "accessibility": null,
    "bestPractices": 0.73,
    "seo": 0.9,
    "total": 170
  },
  "firstContentfulPaint": 13080.164000000002,
  "speedIndex": 52340.97042721316,
  "largestContentfulPaint": 28939.1935,
  "totalBlockingTime": 1486,
  "cumulativeLayoutShift": 0.030157188203599715,
  "timeToInteractive": 30862.54699999999,
  "maxPotentialFirstInputDelay": 498,
  "timeToFirstByte": 9374.452000000001,
  "weight": {
    "summary": "133 requests • 3,028 KiB",
    "total": 3100999,
    "image": 814133,
    "imageCount": 48,
    "script": 1558262,
    "scriptCount": 41,
    "document": 80999,
    "font": 499426,
    "fontCount": 14,
    "stylesheet": 115869,
    "stylesheetCount": 8,
    "thirdParty": 1725969,
    "thirdPartyCount": 66
  },
  "run": {
    "number": 3,
    "total": 3
  },
  "axe": {
    "error": "{\"name\":\"TimeoutError\"}"
  }
}