{
  "url": "https://www.dek-d.com/",
  "requestedUrl": "https://www.dek-d.com/",
  "timestamp": 1712668179398,
  "ranks": {
    "hundos": 10,
    "performance": 8,
    "accessibility": 8,
    "cumulative": 9
  },
  "lighthouse": {
    "version": "11.7.1",
    "performance": 0.29,
    "accessibility": 0.65,
    "bestPractices": 0.48,
    "seo": 0.91,
    "total": 233
  },
  "firstContentfulPaint": 4504.892020000001,
  "firstMeaningfulPaint": 8692.821330000002,
  "speedIndex": 17828.369181654125,
  "largestContentfulPaint": 28505.693839999993,
  "totalBlockingTime": 1970.9999999999964,
  "cumulativeLayoutShift": 0.009394998599008697,
  "timeToInteractive": 29884.16152000001,
  "maxPotentialFirstInputDelay": 604,
  "timeToFirstByte": 963,
  "weight": {
    "summary": "209 requests • 4.2 MiB",
    "total": 4418231,
    "image": 686506,
    "imageCount": 56,
    "script": 2702075,
    "scriptCount": 64,
    "document": 114155,
    "font": 501250,
    "fontCount": 15,
    "stylesheet": 260084,
    "stylesheetCount": 8,
    "thirdParty": 2623727,
    "thirdPartyCount": 19
  },
  "run": {
    "number": 1,
    "total": 3
  },
  "sidequests": {
    "-weight.total": 9,
    "+weight.total": 2,
    "-weight.document": 9,
    "+weight.document": 2,
    "-weight.script": 10,
    "+weight.script": 1,
    "-weight.image": 6,
    "+weight.image": 5,
    "-weight.font": 7,
    "+weight.font": 2,
    "+weight.fontCount": 1,
    "-timeToFirstByte": 9,
    "-totalBlockingTime": 8,
    "-largestContentfulPaint": 10
  },
  "axe": {
    "passes": 2186,
    "violations": 392
  }
}