{
  "url": "https://www.zachleat.com/web/",
  "requestedUrl": "https://www.zachleat.com/web/",
  "timestamp": 1715202745718,
  "ranks": {
    "hundos": 8,
    "performance": 2,
    "accessibility": 1,
    "cumulative": 8
  },
  "lighthouse": {
    "version": "11.7.1",
    "performance": 1,
    "accessibility": 1,
    "bestPractices": 0.93,
    "seo": 1,
    "total": 393
  },
  "firstContentfulPaint": 1145.1999999999998,
  "firstMeaningfulPaint": 1145.1999999999998,
  "speedIndex": 1145.1999999999998,
  "largestContentfulPaint": 1724.0619999999997,
  "totalBlockingTime": 0,
  "cumulativeLayoutShift": 0,
  "timeToInteractive": 1145.1999999999998,
  "maxPotentialFirstInputDelay": 36,
  "timeToFirstByte": 41.846999999999994,
  "weight": {
    "summary": "22 requests • 120.2 KiB",
    "total": 123133,
    "image": 21326,
    "imageCount": 13,
    "script": 5233,
    "scriptCount": 1,
    "document": 34012,
    "font": 58324,
    "fontCount": 5,
    "stylesheet": 4061,
    "stylesheetCount": 1,
    "thirdParty": 19239,
    "thirdPartyCount": 2
  },
  "run": {
    "number": 1,
    "total": 3
  },
  "sidequests": {
    "-weight.total": 6,
    "+weight.total": 6,
    "-weight.document": 8,
    "+weight.document": 4,
    "-weight.script": 2,
    "+weight.script": 5,
    "-weight.image": 4,
    "+weight.image": 8,
    "-weight.font": 5,
    "+weight.font": 5,
    "+weight.fontCount": 1,
    "-timeToFirstByte": 8,
    "-totalBlockingTime": 1,
    "-largestContentfulPaint": 7
  },
  "axe": {
    "passes": 4679,
    "violations": 0
  }
}