{
  "url": "https://jamstackconf.com/",
  "requestedUrl": "https://jamstackconf.com/",
  "timestamp": 1607224526833,
  "ranks": {
    "hundos": 17,
    "performance": 1,
    "accessibility": 18,
    "cumulative": 17
  },
  "lighthouse": {
    "version": "6.5.0",
    "performance": 1,
    "accessibility": 0.95,
    "bestPractices": 0.93,
    "seo": 1,
    "total": 388
  },
  "firstContentfulPaint": 902.0709999999999,
  "speedIndex": 902.0709999999999,
  "largestContentfulPaint": 1586.598,
  "totalBlockingTime": 82,
  "cumulativeLayoutShift": 0,
  "timeToInteractive": 2284.903,
  "maxPotentialFirstInputDelay": 119,
  "timeToFirstByte": 2.4839999999999947,
  "weight": {
    "summary": "16 requests • 175 KiB",
    "total": 179653,
    "image": 33954,
    "imageCount": 2,
    "script": 61153,
    "scriptCount": 3,
    "document": 13893,
    "font": 62843,
    "fontCount": 5,
    "stylesheet": 7216,
    "stylesheetCount": 3,
    "thirdParty": 123767,
    "thirdPartyCount": 11
  },
  "axe": {
    "passes": 770,
    "violations": 16
  }
}