{
  "url": "https://docusaurus.io/",
  "requestedUrl": "https://docusaurus.io/",
  "timestamp": 1652034355539,
  "ranks": {
    "hundos": 10,
    "performance": 9,
    "accessibility": 1,
    "cumulative": 10
  },
  "lighthouse": {
    "version": "9.5.0",
    "performance": 0.6,
    "accessibility": 1,
    "bestPractices": 0.92,
    "seo": 0.96,
    "total": 348
  },
  "firstContentfulPaint": 1103.1550000000002,
  "firstMeaningfulPaint": 2865.3650000000007,
  "speedIndex": 3721.829785078682,
  "largestContentfulPaint": 3257.09,
  "totalBlockingTime": 1187,
  "cumulativeLayoutShift": 0,
  "timeToInteractive": 10236.171999999999,
  "maxPotentialFirstInputDelay": 386,
  "timeToFirstByte": 55.117,
  "weight": {
    "summary": "47 requests • 1,183 KiB",
    "total": 1211304,
    "image": 145325,
    "imageCount": 14,
    "script": 917211,
    "scriptCount": 16,
    "document": 39093,
    "font": 10866,
    "fontCount": 1,
    "stylesheet": 75043,
    "stylesheetCount": 3,
    "thirdParty": 962478,
    "thirdPartyCount": 32
  },
  "run": {
    "number": 2,
    "total": 3
  },
  "axe": {
    "passes": 758,
    "violations": 0
  }
}