{
  "url": "https://docusaurus.io/",
  "requestedUrl": "https://v2.docusaurus.io/",
  "timestamp": 1623429325846,
  "ranks": {
    "hundos": 9,
    "performance": 9,
    "accessibility": 9,
    "cumulative": 9
  },
  "lighthouse": {
    "version": "7.5.0",
    "performance": 0.64,
    "accessibility": 0.96,
    "bestPractices": 0.93,
    "seo": 0.94,
    "total": 347
  },
  "firstContentfulPaint": 3710.0129999999995,
  "speedIndex": 3710.0129999999995,
  "largestContentfulPaint": 4010.013,
  "totalBlockingTime": 546.9999999999995,
  "cumulativeLayoutShift": 0.07771809895833333,
  "timeToInteractive": 5076.012999999999,
  "maxPotentialFirstInputDelay": 433,
  "timeToFirstByte": 58.294,
  "weight": {
    "summary": "26 requests • 299 KiB",
    "total": 306224,
    "image": 63920,
    "imageCount": 10,
    "script": 208917,
    "scriptCount": 8,
    "document": 10003,
    "font": 0,
    "fontCount": 0,
    "stylesheet": 21745,
    "stylesheetCount": 2,
    "thirdParty": 126542,
    "thirdPartyCount": 15
  },
  "run": {
    "number": 1,
    "total": 3
  },
  "axe": {
    "passes": 395,
    "violations": 6
  }
}