{
  "url": "https://www.lazada.co.th///_____tmd_____/punish?x5secdata=xcTx5jF6KsjyN1WCHmnugI52MjFUTE0MCsAsG1e75AwUeEDNOGDRnpZKgmPIWxwFDWOzYF0UHA%2fN1cxF2RAxeHdjIPg6MLExmf2Deru4xbj415LHyUq65lTF9ewBED0RR6q0oxtsUicPtGHA%2bdQhiNcuvCK5RaLy%2fgKde1P67kghf%2b3zZZ3k3fK%2fPz1McOniU%2f5uJRCdJ5CDlDjoWz4UG8bXe1PfZ6yWt23Py5%2fqp%2b7nw%3d__bx__www.lazada.co.th%2f&x5step=1",
  "requestedUrl": "https://www.lazada.co.th/",
  "timestamp": 1698581590587,
  "ranks": {
    "hundos": 4,
    "performance": 2,
    "cumulative": 4
  },
  "lighthouse": {
    "version": "10.4.0",
    "performance": 0.79,
    "accessibility": 0.77,
    "bestPractices": 0.83,
    "seo": 0.85,
    "total": 324
  },
  "firstContentfulPaint": 2645.265,
  "firstMeaningfulPaint": 2705.265,
  "speedIndex": 4151.719691801774,
  "largestContentfulPaint": 4264.7955,
  "totalBlockingTime": 123,
  "cumulativeLayoutShift": 0.0034548450569410367,
  "timeToInteractive": 4421.7235,
  "maxPotentialFirstInputDelay": 206,
  "timeToFirstByte": 298.828,
  "weight": {
    "summary": "26 requests • 293 KiB",
    "total": 300498,
    "image": 83774,
    "imageCount": 5,
    "script": 203506,
    "scriptCount": 15,
    "document": 3618,
    "font": 5790,
    "fontCount": 1,
    "stylesheet": 3570,
    "stylesheetCount": 1,
    "thirdParty": 296641,
    "thirdPartyCount": 21
  },
  "run": {
    "number": 3,
    "total": 3
  },
  "sidequests": {
    "-weight.total": 1,
    "+weight.total": 10,
    "-weight.document": 1,
    "+weight.document": 10,
    "-weight.script": 1,
    "+weight.script": 10,
    "-weight.image": 3,
    "+weight.image": 8,
    "-weight.font": 1,
    "+weight.font": 8,
    "+weight.fontCount": 5,
    "-timeToFirstByte": 7,
    "-totalBlockingTime": 1,
    "-largestContentfulPaint": 4
  }
}