{
  "url": "https://www.zachleat.com/web/speedlify/",
  "requestedUrl": "https://www.zachleat.com/web/speedlify/",
  "timestamp": 1642265230138,
  "ranks": {
    "hundos": 11,
    "performance": 11,
    "accessibility": 9,
    "cumulative": 11
  },
  "lighthouse": {
    "version": "6.5.0",
    "performance": 0.95,
    "accessibility": 0.92,
    "bestPractices": 0.93,
    "seo": 0.93,
    "total": 373
  },
  "firstContentfulPaint": 2149.913,
  "speedIndex": 2149.913,
  "largestContentfulPaint": 2149.913,
  "totalBlockingTime": 46,
  "cumulativeLayoutShift": 0.00099853515625,
  "timeToInteractive": 4672.997,
  "maxPotentialFirstInputDelay": 112,
  "timeToFirstByte": 76.93800000000002,
  "weight": {
    "summary": "25 requests • 779 KiB",
    "total": 798043,
    "image": 668770,
    "imageCount": 16,
    "script": 21273,
    "scriptCount": 3,
    "document": 60553,
    "font": 43038,
    "fontCount": 3,
    "stylesheet": 3669,
    "stylesheetCount": 1,
    "thirdParty": 42957,
    "thirdPartyCount": 9
  },
  "run": {
    "number": 3,
    "total": 3
  },
  "axe": {
    "passes": 5730,
    "violations": 3
  }
}