{
  "url": "https://symfony.com/",
  "requestedUrl": "https://symfony.com/",
  "timestamp": 1669948281254,
  "ranks": {
    "hundos": 4,
    "performance": 4,
    "accessibility": 4,
    "cumulative": 4
  },
  "lighthouse": {
    "version": "9.6.8",
    "performance": 0.77,
    "accessibility": 0.92,
    "bestPractices": 0.92,
    "seo": 0.95,
    "total": 356
  },
  "firstContentfulPaint": 1379.688,
  "firstMeaningfulPaint": 1379.688,
  "speedIndex": 2472.633557797726,
  "largestContentfulPaint": 1995.8930000000003,
  "totalBlockingTime": 777.0340000000001,
  "cumulativeLayoutShift": 0.0556419677734375,
  "timeToInteractive": 5727.963,
  "maxPotentialFirstInputDelay": 559,
  "timeToFirstByte": 490.378,
  "weight": {
    "summary": "39 requests • 402 KiB",
    "total": 411881,
    "image": 96388,
    "imageCount": 14,
    "script": 253950,
    "scriptCount": 15,
    "document": 15889,
    "font": 0,
    "fontCount": 0,
    "stylesheet": 37606,
    "stylesheetCount": 5,
    "thirdParty": 55043,
    "thirdPartyCount": 10
  },
  "run": {
    "number": 3,
    "total": 3
  },
  "sidequests": {
    "-weight.total": 3,
    "+weight.total": 3,
    "-weight.document": 3,
    "+weight.document": 3,
    "-weight.script": 4,
    "+weight.script": 2,
    "-weight.image": 3,
    "+weight.image": 3,
    "-weight.font": 1,
    "+weight.font": 5,
    "+weight.fontCount": 4,
    "-timeToFirstByte": 5,
    "-totalBlockingTime": 3,
    "-largestContentfulPaint": 2
  },
  "axe": {
    "passes": 822,
    "violations": 37
  }
}