{
  "url": "https://symfony.com/",
  "requestedUrl": "https://symfony.com/",
  "timestamp": 1713370021105,
  "ranks": {
    "hundos": 2,
    "performance": 2,
    "accessibility": 3,
    "cumulative": 2
  },
  "lighthouse": {
    "version": "11.7.1",
    "performance": 0.98,
    "accessibility": 0.9,
    "bestPractices": 1,
    "seo": 1,
    "total": 388
  },
  "firstContentfulPaint": 1514.9344999999998,
  "firstMeaningfulPaint": 1965.4834999999998,
  "speedIndex": 1924.9830327484901,
  "largestContentfulPaint": 2265.8495,
  "totalBlockingTime": 0,
  "cumulativeLayoutShift": 0,
  "timeToInteractive": 1965.4834999999998,
  "maxPotentialFirstInputDelay": 47,
  "timeToFirstByte": 21.719,
  "weight": {
    "summary": "41 requests • 263.7 KiB",
    "total": 270015,
    "image": 64726,
    "imageCount": 6,
    "script": 149972,
    "scriptCount": 21,
    "document": 43620,
    "font": 0,
    "fontCount": 0,
    "stylesheet": 3825,
    "stylesheetCount": 10,
    "thirdParty": 37208,
    "thirdPartyCount": 4
  },
  "run": {
    "number": 2,
    "total": 3
  },
  "sidequests": {
    "-weight.total": 3,
    "+weight.total": 3,
    "-weight.document": 3,
    "+weight.document": 3,
    "-weight.script": 3,
    "+weight.script": 3,
    "-weight.image": 3,
    "+weight.image": 3,
    "-weight.font": 1,
    "+weight.font": 5,
    "+weight.fontCount": 3,
    "-timeToFirstByte": 1,
    "-totalBlockingTime": 1,
    "-largestContentfulPaint": 2
  },
  "axe": {
    "passes": 801,
    "violations": 9
  }
}