{
  "url": "https://mochajs.org/",
  "requestedUrl": "https://mochajs.org/",
  "timestamp": 1695525414510,
  "ranks": {
    "hundos": 8,
    "performance": 6,
    "accessibility": 8,
    "cumulative": 8
  },
  "lighthouse": {
    "version": "10.4.0",
    "performance": 0.94,
    "accessibility": 0.74,
    "bestPractices": 0.92,
    "seo": 0.66,
    "total": 326
  },
  "firstContentfulPaint": 1496.127,
  "firstMeaningfulPaint": 1677.627,
  "speedIndex": 2007.6927706757788,
  "largestContentfulPaint": 1677.627,
  "totalBlockingTime": 264,
  "cumulativeLayoutShift": 0.0030190330559841656,
  "timeToInteractive": 2542.37,
  "maxPotentialFirstInputDelay": 341,
  "timeToFirstByte": 42.79299999999998,
  "weight": {
    "summary": "7 requests • 180 KiB",
    "total": 184427,
    "image": 72320,
    "imageCount": 3,
    "script": 40226,
    "scriptCount": 1,
    "document": 61779,
    "font": 0,
    "fontCount": 0,
    "stylesheet": 9937,
    "stylesheetCount": 1,
    "thirdParty": 41236,
    "thirdPartyCount": 4
  },
  "run": {
    "number": 1,
    "total": 3
  },
  "sidequests": {
    "-weight.total": 3,
    "+weight.total": 8,
    "-weight.document": 9,
    "+weight.document": 2,
    "-weight.script": 1,
    "+weight.script": 9,
    "-weight.image": 5,
    "+weight.image": 6,
    "-weight.font": 1,
    "+weight.font": 8,
    "+weight.fontCount": 6,
    "-timeToFirstByte": 5,
    "-totalBlockingTime": 6,
    "-largestContentfulPaint": 2
  },
  "axe": {
    "passes": 10022,
    "violations": 930
  }
}