{
  "url": "https://www.kapook.com/",
  "requestedUrl": "https://www.kapook.com/",
  "timestamp": 1605961391994,
  "ranks": {
    "hundos": 9,
    "performance": 5,
    "accessibility": 10,
    "cumulative": 9
  },
  "lighthouse": {
    "version": "6.4.1",
    "performance": 0.3,
    "accessibility": 0.66,
    "bestPractices": 0.57,
    "seo": 0.93,
    "total": 246
  },
  "firstContentfulPaint": 2300.8720000000003,
  "speedIndex": 9006.177009266361,
  "largestContentfulPaint": 6310.112000000001,
  "totalBlockingTime": 671.4999999999991,
  "cumulativeLayoutShift": 0.6835472342173259,
  "timeToInteractive": 19005.0975,
  "maxPotentialFirstInputDelay": 215,
  "timeToFirstByte": 556.332,
  "weight": {
    "summary": "181 requests • 2,220 KiB",
    "total": 2273487,
    "image": 1372538,
    "imageCount": 63,
    "script": 766399,
    "scriptCount": 45,
    "document": 65861,
    "font": 20398,
    "fontCount": 1,
    "stylesheet": 3419,
    "stylesheetCount": 2,
    "thirdParty": 876929,
    "thirdPartyCount": 139
  },
  "axe": {
    "passes": 5450,
    "violations": 549
  }
}