{
  "url": "https://www.netlify.com/privacy/",
  "requestedUrl": "https://www.netlify.com/privacy/",
  "timestamp": 1641231133136,
  "ranks": {
    "hundos": 5,
    "performance": 5,
    "accessibility": 7,
    "cumulative": 5
  },
  "lighthouse": {
    "version": "6.5.0",
    "performance": 0.86,
    "accessibility": 0.96,
    "bestPractices": 1,
    "seo": 1,
    "total": 382
  },
  "firstContentfulPaint": 1397.788,
  "speedIndex": 1686.8155132204338,
  "largestContentfulPaint": 1397.788,
  "totalBlockingTime": 490,
  "cumulativeLayoutShift": 0.016038411458333332,
  "timeToInteractive": 5626.518999999999,
  "maxPotentialFirstInputDelay": 334,
  "timeToFirstByte": 275.88100000000003,
  "weight": {
    "summary": "35 requests • 393 KiB",
    "total": 402486,
    "image": 7469,
    "imageCount": 10,
    "script": 220430,
    "scriptCount": 10,
    "document": 44956,
    "font": 124286,
    "fontCount": 5,
    "stylesheet": 0,
    "stylesheetCount": 0,
    "thirdParty": 221973,
    "thirdPartyCount": 27
  },
  "run": {
    "number": 2,
    "total": 3
  },
  "axe": {
    "passes": 1014,
    "violations": 2
  }
}