{
  "url": "https://mthai.com/",
  "requestedUrl": "https://mthai.com/",
  "timestamp": 1595333508888,
  "ranks": {
    "hundos": 5,
    "performance": 5,
    "accessibility": 2,
    "cumulative": 5
  },
  "lighthouse": {
    "version": "6.1.1",
    "performance": 0.37,
    "accessibility": 0.94,
    "bestPractices": 0.69,
    "seo": 0.98,
    "total": 298
  },
  "firstContentfulPaint": 2622.1040000000003,
  "speedIndex": 11351.555097827439,
  "largestContentfulPaint": 14983.136999999995,
  "totalBlockingTime": 378,
  "cumulativeLayoutShift": 0.2748435329861111,
  "timeToInteractive": 13087.992999999999,
  "maxPotentialFirstInputDelay": 274,
  "timeToFirstByte": 460.132,
  "weight": {
    "summary": "116 requests • 2,860 KiB",
    "total": 2928444,
    "image": 1940173,
    "imageCount": 58,
    "script": 689627,
    "scriptCount": 21,
    "document": 42580,
    "font": 183741,
    "fontCount": 2,
    "stylesheet": 47677,
    "stylesheetCount": 2,
    "thirdParty": 2505410,
    "thirdPartyCount": 104
  },
  "axe": {
    "passes": 752,
    "violations": 6
  }
}