{
  "url": "https://codeigniter.com/",
  "requestedUrl": "https://codeigniter.com/",
  "timestamp": 1624897756024,
  "ranks": {
    "hundos": 4,
    "performance": 3,
    "accessibility": 3,
    "cumulative": 4
  },
  "lighthouse": {
    "version": "7.5.0",
    "performance": 0.86,
    "accessibility": 0.95,
    "bestPractices": 0.73,
    "seo": 0.92,
    "total": 346
  },
  "firstContentfulPaint": 2310.755,
  "speedIndex": 2945.486952168537,
  "largestContentfulPaint": 3479.517,
  "totalBlockingTime": 132.5,
  "cumulativeLayoutShift": 0.00041479301452636725,
  "timeToInteractive": 4561.56,
  "maxPotentialFirstInputDelay": 117,
  "timeToFirstByte": 314.187,
  "weight": {
    "summary": "26 requests • 376 KiB",
    "total": 385028,
    "image": 13515,
    "imageCount": 3,
    "script": 86094,
    "scriptCount": 8,
    "document": 123668,
    "font": 124663,
    "fontCount": 4,
    "stylesheet": 36487,
    "stylesheetCount": 6,
    "thirdParty": 339073,
    "thirdPartyCount": 18
  },
  "run": {
    "number": 1,
    "total": 3
  },
  "axe": {
    "passes": 298,
    "violations": 44
  }
}