{
  "url": "https://www.wongnai.com/",
  "requestedUrl": "https://www.wongnai.com/",
  "timestamp": 1621184231664,
  "ranks": {
    "hundos": 7,
    "performance": 4,
    "accessibility": 11,
    "cumulative": 7
  },
  "lighthouse": {
    "version": "7.4.0",
    "performance": 0.19,
    "accessibility": 0.6,
    "bestPractices": 0.8,
    "seo": 0.98,
    "total": 257
  },
  "firstContentfulPaint": 3314.148,
  "speedIndex": 8625.053641903305,
  "largestContentfulPaint": 14616.094999999998,
  "totalBlockingTime": 2940.5,
  "cumulativeLayoutShift": 0.009658185958862305,
  "timeToInteractive": 14466.095,
  "maxPotentialFirstInputDelay": 1046,
  "timeToFirstByte": 1652.451,
  "weight": {
    "summary": "109 requests • 2,101 KiB",
    "total": 2151906,
    "image": 890768,
    "imageCount": 63,
    "script": 986234,
    "scriptCount": 28,
    "document": 132044,
    "font": 87711,
    "fontCount": 3,
    "stylesheet": 39019,
    "stylesheetCount": 1,
    "thirdParty": 289723,
    "thirdPartyCount": 34
  },
  "run": {
    "number": 2,
    "total": 3
  },
  "axe": {
    "passes": 80,
    "violations": 9
  }
}