{
  "url": "https://www.thewdhanat.com/blog/",
  "requestedUrl": "https://www.thewdhanat.com/blog/",
  "timestamp": 1670620523658,
  "ranks": {
    "hundos": 2,
    "performance": 3,
    "accessibility": 5,
    "cumulative": 2
  },
  "lighthouse": {
    "version": "9.6.8",
    "performance": 0.96,
    "accessibility": 1,
    "bestPractices": 1,
    "seo": 1,
    "total": 396
  },
  "firstContentfulPaint": 906.287,
  "firstMeaningfulPaint": 906.287,
  "speedIndex": 906.287,
  "largestContentfulPaint": 1564.4600000000005,
  "totalBlockingTime": 208,
  "cumulativeLayoutShift": 0,
  "timeToInteractive": 2754.3720000000008,
  "maxPotentialFirstInputDelay": 180,
  "timeToFirstByte": 9.482,
  "weight": {
    "summary": "14 requests • 106 KiB",
    "total": 108810,
    "image": 3185,
    "imageCount": 2,
    "script": 81991,
    "scriptCount": 3,
    "document": 10006,
    "font": 2362,
    "fontCount": 1,
    "stylesheet": 8208,
    "stylesheetCount": 3,
    "thirdParty": 88715,
    "thirdPartyCount": 8
  },
  "run": {
    "number": 3,
    "total": 3
  },
  "sidequests": {
    "-weight.total": 4,
    "+weight.total": 2,
    "-weight.document": 1,
    "+weight.document": 5,
    "-weight.script": 2,
    "+weight.script": 2,
    "-weight.image": 4,
    "+weight.image": 1,
    "-weight.font": 1,
    "+weight.font": 2,
    "+weight.fontCount": 1,
    "-timeToFirstByte": 2,
    "-totalBlockingTime": 3,
    "-largestContentfulPaint": 1
  },
  "axe": {
    "passes": 246,
    "violations": 0
  }
}