{
  "url": "https://www.netlify.com/for/ecommerce/",
  "requestedUrl": "https://www.netlify.com/for/ecommerce/",
  "timestamp": 1639589415280,
  "ranks": {
    "hundos": 9,
    "performance": 6,
    "accessibility": 11,
    "cumulative": 9
  },
  "lighthouse": {
    "version": "6.5.0",
    "performance": 0.79,
    "accessibility": 0.95,
    "bestPractices": 1,
    "seo": 1,
    "total": 374
  },
  "firstContentfulPaint": 1453.9429999999998,
  "speedIndex": 1794.9361750450623,
  "largestContentfulPaint": 2456.3149999999996,
  "totalBlockingTime": 552.4999999999995,
  "cumulativeLayoutShift": 0.230153151512146,
  "timeToInteractive": 5998.6885,
  "maxPotentialFirstInputDelay": 388,
  "timeToFirstByte": 256.32300000000004,
  "weight": {
    "summary": "39 requests • 518 KiB",
    "total": 529943,
    "image": 103988,
    "imageCount": 14,
    "script": 221213,
    "scriptCount": 10,
    "document": 74915,
    "font": 124249,
    "fontCount": 5,
    "stylesheet": 0,
    "stylesheetCount": 0,
    "thirdParty": 222209,
    "thirdPartyCount": 27
  },
  "run": {
    "number": 2,
    "total": 3
  },
  "axe": {
    "passes": 1445,
    "violations": 4
  }
}