{
  "url": "https://laravel.com/",
  "requestedUrl": "https://laravel.com/",
  "timestamp": 1638717718103,
  "ranks": {
    "hundos": 4,
    "performance": 4,
    "accessibility": 2,
    "cumulative": 4
  },
  "lighthouse": {
    "version": "6.5.0",
    "performance": 0.56,
    "accessibility": 0.96,
    "bestPractices": 0.93,
    "seo": 0.85,
    "total": 330
  },
  "firstContentfulPaint": 3780.1849999999995,
  "speedIndex": 3780.1849999999995,
  "largestContentfulPaint": 4708.233,
  "totalBlockingTime": 706,
  "cumulativeLayoutShift": 0,
  "timeToInteractive": 5038.393,
  "maxPotentialFirstInputDelay": 608,
  "timeToFirstByte": 25.969,
  "weight": {
    "summary": "45 requests • 6,742 KiB",
    "total": 6903573,
    "image": 402137,
    "imageCount": 33,
    "script": 70548,
    "scriptCount": 2,
    "document": 10653,
    "font": 71371,
    "fontCount": 3,
    "stylesheet": 399394,
    "stylesheetCount": 3,
    "thirdParty": 90559,
    "thirdPartyCount": 7
  },
  "run": {
    "number": 3,
    "total": 3
  },
  "axe": {
    "passes": 806,
    "violations": 96
  }
}