{
  "url": "https://www.thewdhanat.com/",
  "requestedUrl": "https://www.thewdhanat.com/",
  "timestamp": 1633547928950,
  "ranks": {
    "hundos": 2,
    "performance": 3,
    "accessibility": 3,
    "cumulative": 2
  },
  "lighthouse": {
    "version": "7.5.0",
    "performance": 0.99,
    "accessibility": 1,
    "bestPractices": 1,
    "seo": 1,
    "total": 399
  },
  "firstContentfulPaint": 871.0709999999999,
  "speedIndex": 871.0709999999999,
  "largestContentfulPaint": 1553.4619999999995,
  "totalBlockingTime": 90,
  "cumulativeLayoutShift": 0,
  "timeToInteractive": 3745.528,
  "maxPotentialFirstInputDelay": 115,
  "timeToFirstByte": 12.546999999999997,
  "weight": {
    "summary": "15 requests • 134 KiB",
    "total": 137445,
    "image": 2567,
    "imageCount": 2,
    "script": 113430,
    "scriptCount": 5,
    "document": 9438,
    "font": 2626,
    "fontCount": 1,
    "stylesheet": 6008,
    "stylesheetCount": 2,
    "thirdParty": 118521,
    "thirdPartyCount": 10
  },
  "run": {
    "number": 1,
    "total": 3
  },
  "axe": {
    "passes": 371,
    "violations": 0
  }
}