{
  "url": "https://www.linkedin.com/checkpoint/challengesV2/AQGgpbEGMlhZlAAAAYoJab7yv0ePWHF1NMGsv9mvg6RhMh-8oZhljoy4QHq_dLXDxN3p1UVfl6mmiML_gA6RG5Lg0a9J9HR4EQ",
  "requestedUrl": "https://www.linkedin.com/in/thew-dhanat",
  "timestamp": 1692375053196,
  "ranks": {
    "hundos": 6,
    "performance": 7,
    "cumulative": 6
  },
  "lighthouse": {
    "version": "10.4.0",
    "performance": 0.63,
    "accessibility": 1,
    "bestPractices": 0.92,
    "seo": 0.83,
    "total": 338
  },
  "firstContentfulPaint": 2375.7529999999997,
  "firstMeaningfulPaint": 2450.9649999999997,
  "speedIndex": 4738.7969907144125,
  "largestContentfulPaint": 2450.9649999999997,
  "totalBlockingTime": 2297.7565,
  "cumulativeLayoutShift": 0,
  "timeToInteractive": 7923.933499999999,
  "maxPotentialFirstInputDelay": 772,
  "timeToFirstByte": 372.944,
  "weight": {
    "summary": "46 requests • 576 KiB",
    "total": 589614,
    "image": 0,
    "imageCount": 0,
    "script": 537929,
    "scriptCount": 21,
    "document": 23156,
    "font": 0,
    "fontCount": 0,
    "stylesheet": 14218,
    "stylesheetCount": 2,
    "thirdParty": 564118,
    "thirdPartyCount": 34
  },
  "run": {
    "number": 3,
    "total": 3
  },
  "sidequests": {
    "-weight.total": 6,
    "+weight.total": 4,
    "-weight.document": 7,
    "+weight.document": 3,
    "-weight.script": 7,
    "+weight.script": 2,
    "-weight.image": 1,
    "+weight.image": 8,
    "-weight.font": 1,
    "+weight.font": 7,
    "+weight.fontCount": 4,
    "-timeToFirstByte": 8,
    "-totalBlockingTime": 8,
    "-largestContentfulPaint": 6
  }
}