{
  "url": "https://www.kotchasan.com/",
  "requestedUrl": "https://kotchasan.com/",
  "timestamp": 1687007217726,
  "ranks": {
    "hundos": 5,
    "performance": 5,
    "accessibility": 4,
    "cumulative": 5
  },
  "lighthouse": {
    "version": "10.3.0",
    "performance": 0.47,
    "accessibility": 0.79,
    "bestPractices": 0.83,
    "seo": 1,
    "total": 316
  },
  "firstContentfulPaint": 3060.9620000000004,
  "firstMeaningfulPaint": 3361.6035,
  "speedIndex": 9148.944313116692,
  "largestContentfulPaint": 3842.635,
  "totalBlockingTime": 1793.0000000000005,
  "cumulativeLayoutShift": 0.06539230495170156,
  "timeToInteractive": 14687.579999999998,
  "maxPotentialFirstInputDelay": 562,
  "timeToFirstByte": 257.53,
  "weight": {
    "summary": "154 requests • 4,310 KiB",
    "total": 4413542,
    "image": 701358,
    "imageCount": 38,
    "script": 722555,
    "scriptCount": 48,
    "document": 159121,
    "font": 148251,
    "fontCount": 7,
    "stylesheet": 43038,
    "stylesheetCount": 6,
    "thirdParty": 4214909,
    "thirdPartyCount": 146
  },
  "run": {
    "number": 2,
    "total": 3
  },
  "sidequests": {
    "-weight.total": 5,
    "+weight.total": 1,
    "-weight.document": 5,
    "+weight.document": 1,
    "-weight.script": 5,
    "+weight.script": 1,
    "-weight.image": 4,
    "+weight.image": 2,
    "-weight.font": 4,
    "+weight.font": 1,
    "+weight.fontCount": 1,
    "-timeToFirstByte": 4,
    "-totalBlockingTime": 4,
    "-largestContentfulPaint": 5
  },
  "axe": {
    "passes": 275,
    "violations": 6
  }
}