{
  "url": "https://record-collector.net/",
  "requestedUrl": "https://record-collector.net/",
  "timestamp": 1711141647053,
  "ranks": {
    "hundos": 2,
    "performance": 1,
    "accessibility": 2,
    "cumulative": 2
  },
  "lighthouse": {
    "version": "11.7.0",
    "performance": 1,
    "accessibility": 1,
    "bestPractices": 1,
    "seo": 1,
    "total": 400
  },
  "firstContentfulPaint": 835.2745,
  "firstMeaningfulPaint": 835.2745,
  "speedIndex": 835.2745,
  "largestContentfulPaint": 1137.2745,
  "totalBlockingTime": 0,
  "cumulativeLayoutShift": 0,
  "timeToInteractive": 835.2745,
  "maxPotentialFirstInputDelay": 48,
  "timeToFirstByte": 59.60600000000001,
  "weight": {
    "summary": "4 requests • 44.9 KiB",
    "total": 45939,
    "image": 5792,
    "imageCount": 1,
    "script": 30529,
    "scriptCount": 1,
    "document": 2909,
    "font": 0,
    "fontCount": 0,
    "stylesheet": 6709,
    "stylesheetCount": 1,
    "thirdParty": 0,
    "thirdPartyCount": 0
  },
  "run": {
    "number": 1,
    "total": 3
  },
  "sidequests": {
    "-weight.total": 1,
    "+weight.total": 14,
    "-weight.document": 1,
    "+weight.document": 14,
    "-weight.script": 3,
    "+weight.script": 12,
    "-weight.image": 1,
    "+weight.image": 13,
    "-weight.font": 1,
    "+weight.font": 11,
    "+weight.fontCount": 6,
    "-timeToFirstByte": 11,
    "-totalBlockingTime": 1,
    "-largestContentfulPaint": 2
  },
  "axe": {
    "passes": 165,
    "violations": 0
  }
}