{
  "url": "https://www.zachleat.com/about/",
  "requestedUrl": "https://www.zachleat.com/web/about/",
  "timestamp": 1703352120975,
  "ranks": {
    "hundos": 11,
    "performance": 11,
    "accessibility": 10,
    "cumulative": 11
  },
  "lighthouse": {
    "version": "10.4.0",
    "performance": 0.97,
    "accessibility": 0.98,
    "bestPractices": 0.92,
    "seo": 1,
    "total": 387
  },
  "firstContentfulPaint": 1066.084,
  "firstMeaningfulPaint": 1066.084,
  "speedIndex": 1066.084,
  "largestContentfulPaint": 1355.611,
  "totalBlockingTime": 0,
  "cumulativeLayoutShift": 0.10077618272355261,
  "timeToInteractive": 1066.084,
  "maxPotentialFirstInputDelay": 27,
  "timeToFirstByte": 31.931,
  "weight": {
    "summary": "28 requests • 213 KiB",
    "total": 218462,
    "image": 121202,
    "imageCount": 18,
    "script": 5244,
    "scriptCount": 1,
    "document": 17097,
    "font": 70780,
    "fontCount": 5,
    "stylesheet": 3825,
    "stylesheetCount": 1,
    "thirdParty": 22201,
    "thirdPartyCount": 14
  },
  "run": {
    "number": 3,
    "total": 3
  },
  "sidequests": {
    "-weight.total": 8,
    "+weight.total": 4,
    "-weight.document": 3,
    "+weight.document": 9,
    "-weight.script": 5,
    "+weight.script": 5,
    "-weight.image": 9,
    "+weight.image": 3,
    "-weight.font": 9,
    "+weight.font": 1,
    "+weight.fontCount": 1,
    "-timeToFirstByte": 2,
    "-totalBlockingTime": 1,
    "-largestContentfulPaint": 5
  },
  "axe": {
    "passes": 733,
    "violations": 11
  }
}