{
  "url": "https://www.thewdhanat.com/awesome/",
  "requestedUrl": "https://www.thewdhanat.com/awesome/",
  "timestamp": 1642357560791,
  "ranks": {
    "hundos": 4,
    "performance": 4,
    "accessibility": 1,
    "cumulative": 4
  },
  "lighthouse": {
    "version": "6.5.0",
    "performance": 0.97,
    "accessibility": 1,
    "bestPractices": 1,
    "seo": 1,
    "total": 397
  },
  "firstContentfulPaint": 1217.6569999999997,
  "speedIndex": 1217.6569999999997,
  "largestContentfulPaint": 1904.8879999999995,
  "totalBlockingTime": 93,
  "cumulativeLayoutShift": 0,
  "timeToInteractive": 4233.434499999999,
  "maxPotentialFirstInputDelay": 100,
  "timeToFirstByte": 196.308,
  "weight": {
    "summary": "29 requests • 251 KiB",
    "total": 257521,
    "image": 106433,
    "imageCount": 16,
    "script": 124028,
    "scriptCount": 5,
    "document": 14847,
    "font": 2361,
    "fontCount": 1,
    "stylesheet": 6256,
    "stylesheetCount": 2,
    "thirdParty": 128481,
    "thirdPartyCount": 10
  },
  "run": {
    "number": 1,
    "total": 3
  },
  "axe": {
    "passes": 829,
    "violations": 0
  }
}