{
  "url": "https://www.thewdhanat.com/awesome/",
  "requestedUrl": "https://www.thewdhanat.com/awesome/",
  "timestamp": 1621488367754,
  "ranks": {
    "hundos": 1,
    "performance": 4,
    "accessibility": 1,
    "cumulative": 1
  },
  "lighthouse": {
    "version": "7.5.0",
    "performance": 0.98,
    "accessibility": 1,
    "bestPractices": 1,
    "seo": 1,
    "total": 398
  },
  "firstContentfulPaint": 912.12,
  "speedIndex": 912.12,
  "largestContentfulPaint": 1532.8000000000002,
  "totalBlockingTime": 99.00000000000023,
  "cumulativeLayoutShift": 0,
  "timeToInteractive": 3967.3980000000006,
  "maxPotentialFirstInputDelay": 107,
  "timeToFirstByte": 79.837,
  "weight": {
    "summary": "30 requests • 330 KiB",
    "total": 337917,
    "image": 208837,
    "imageCount": 17,
    "script": 106317,
    "scriptCount": 5,
    "document": 11799,
    "font": 2326,
    "fontCount": 1,
    "stylesheet": 5265,
    "stylesheetCount": 2,
    "thirdParty": 110341,
    "thirdPartyCount": 10
  },
  "run": {
    "number": 2,
    "total": 3
  },
  "axe": {
    "passes": 674,
    "violations": 0
  }
}