{
  "url": "https://disjfa.github.io/eleventy-encore/",
  "requestedUrl": "https://disjfa.github.io/eleventy-encore/",
  "timestamp": 1600009529995,
  "ranks": {
    "hundos": 16,
    "performance": 18,
    "accessibility": 14,
    "cumulative": 17
  },
  "lighthouse": {
    "version": "6.3.0",
    "performance": 0.99,
    "accessibility": 0.95,
    "bestPractices": 1,
    "seo": 0.85,
    "total": 379
  },
  "firstContentfulPaint": 1138.0140000000001,
  "speedIndex": 1138.0140000000001,
  "largestContentfulPaint": 1918.6890000000003,
  "totalBlockingTime": 27.5,
  "cumulativeLayoutShift": 0,
  "timeToInteractive": 2819.5890000000004,
  "maxPotentialFirstInputDelay": 105,
  "timeToFirstByte": 78.519,
  "weight": {
    "summary": "7 requests • 312 KiB",
    "total": 319829,
    "image": 63425,
    "imageCount": 1,
    "script": 61408,
    "scriptCount": 2,
    "document": 1986,
    "font": 156546,
    "fontCount": 2,
    "stylesheet": 36464,
    "stylesheetCount": 1,
    "thirdParty": 63425,
    "thirdPartyCount": 1
  },
  "axe": {
    "passes": 146,
    "violations": 23
  }
}