{
  "url": "https://www.netlify.com/with/drupal/",
  "requestedUrl": "https://www.netlify.com/with/drupal/",
  "timestamp": 1635006729265,
  "ranks": {
    "hundos": 8,
    "performance": 11,
    "accessibility": 8,
    "cumulative": 8
  },
  "lighthouse": {
    "version": "6.5.0",
    "performance": 0.81,
    "accessibility": 0.97,
    "bestPractices": 1,
    "seo": 1,
    "total": 378
  },
  "firstContentfulPaint": 1386.7690000000002,
  "speedIndex": 1687.688869186095,
  "largestContentfulPaint": 2599.92,
  "totalBlockingTime": 550,
  "cumulativeLayoutShift": 0.06708333333333333,
  "timeToInteractive": 5526.2375,
  "maxPotentialFirstInputDelay": 323,
  "timeToFirstByte": 4.16,
  "weight": {
    "summary": "36 requests • 589 KiB",
    "total": 602654,
    "image": 175159,
    "imageCount": 11,
    "script": 219146,
    "scriptCount": 10,
    "document": 79049,
    "font": 124065,
    "fontCount": 5,
    "stylesheet": 0,
    "stylesheetCount": 0,
    "thirdParty": 220521,
    "thirdPartyCount": 27
  },
  "run": {
    "number": 3,
    "total": 3
  },
  "axe": {
    "passes": 1383,
    "violations": 2
  }
}