{
  "url": "https://www.netlify.com/with/sitecore/",
  "requestedUrl": "https://www.netlify.com/with/sitecore/",
  "timestamp": 1614327084190,
  "ranks": {
    "hundos": 9,
    "performance": 16,
    "accessibility": 6,
    "cumulative": 10
  },
  "lighthouse": {
    "version": "6.5.0",
    "performance": 0.94,
    "accessibility": 0.98,
    "bestPractices": 1,
    "seo": 1,
    "total": 392
  },
  "firstContentfulPaint": 1463.901,
  "speedIndex": 1747.8939753869395,
  "largestContentfulPaint": 2357.927,
  "totalBlockingTime": 162.99999999999955,
  "cumulativeLayoutShift": 0.12914669778611926,
  "timeToInteractive": 4946.391,
  "maxPotentialFirstInputDelay": 239.9999999999991,
  "timeToFirstByte": 344.476,
  "weight": {
    "summary": "35 requests • 420 KiB",
    "total": 429599,
    "image": 51248,
    "imageCount": 8,
    "script": 244877,
    "scriptCount": 13,
    "document": 75093,
    "font": 53139,
    "fontCount": 5,
    "stylesheet": 0,
    "stylesheetCount": 0,
    "thirdParty": 244965,
    "thirdPartyCount": 26
  },
  "run": {
    "number": 1,
    "total": 3
  },
  "axe": {
    "passes": 1360,
    "violations": 2
  }
}