{
  "url": "https://gulpjs.com/",
  "requestedUrl": "https://gulpjs.com/",
  "timestamp": 1611042179278,
  "ranks": {
    "hundos": 3,
    "performance": 7,
    "accessibility": 3,
    "cumulative": 3
  },
  "lighthouse": {
    "version": "6.5.0",
    "performance": 0.94,
    "accessibility": 0.97,
    "bestPractices": 1,
    "seo": 0.89,
    "total": 380
  },
  "firstContentfulPaint": 2303.148,
  "speedIndex": 2455.351592914307,
  "largestContentfulPaint": 2303.148,
  "totalBlockingTime": 196,
  "cumulativeLayoutShift": 0.07315901184082031,
  "timeToInteractive": 3798.182,
  "maxPotentialFirstInputDelay": 260,
  "timeToFirstByte": 125.274,
  "weight": {
    "summary": "61 requests • 751 KiB",
    "total": 768655,
    "image": 529437,
    "imageCount": 31,
    "script": 182554,
    "scriptCount": 12,
    "document": 4564,
    "font": 19376,
    "fontCount": 2,
    "stylesheet": 18906,
    "stylesheetCount": 4,
    "thirdParty": 378814,
    "thirdPartyCount": 20
  },
  "run": {
    "number": 2,
    "total": 3
  },
  "axe": {
    "passes": 474,
    "violations": 1
  }
}