{
  "url": "https://gulpjs.com/",
  "requestedUrl": "https://gulpjs.com/",
  "timestamp": 1722877808347,
  "ranks": {
    "hundos": 4,
    "performance": 6,
    "accessibility": 4,
    "cumulative": 4
  },
  "lighthouse": {
    "version": "11.7.1",
    "performance": 0.86,
    "accessibility": 0.95,
    "bestPractices": 1,
    "seo": 0.9,
    "total": 371
  },
  "firstContentfulPaint": 1802.6399999999999,
  "firstMeaningfulPaint": 2038.53,
  "speedIndex": 1869.943459394717,
  "largestContentfulPaint": 3418.42,
  "totalBlockingTime": 134.5,
  "cumulativeLayoutShift": 0.10613858009796533,
  "timeToInteractive": 4144.4310000000005,
  "maxPotentialFirstInputDelay": 179,
  "timeToFirstByte": 114.167,
  "weight": {
    "summary": "45 requests • 625.8 KiB",
    "total": 640860,
    "image": 218697,
    "imageCount": 19,
    "script": 333371,
    "scriptCount": 7,
    "document": 5791,
    "font": 29847,
    "fontCount": 3,
    "stylesheet": 22207,
    "stylesheetCount": 2,
    "thirdParty": 225684,
    "thirdPartyCount": 3
  },
  "run": {
    "number": 1,
    "total": 3
  },
  "sidequests": {
    "-weight.total": 7,
    "+weight.total": 4,
    "-weight.document": 4,
    "+weight.document": 7,
    "-weight.script": 8,
    "+weight.script": 2,
    "-weight.image": 6,
    "+weight.image": 5,
    "-weight.font": 1,
    "+weight.font": 7,
    "+weight.fontCount": 4,
    "-timeToFirstByte": 9,
    "-totalBlockingTime": 4,
    "-largestContentfulPaint": 6
  },
  "axe": {
    "passes": 429,
    "violations": 1
  }
}