{
  "url": "https://webdriver.io/",
  "requestedUrl": "https://webdriver.io/",
  "timestamp": 1674508136056,
  "ranks": {
    "hundos": 10,
    "performance": 10,
    "accessibility": 5,
    "cumulative": 9
  },
  "lighthouse": {
    "version": "9.6.8",
    "performance": 0.37,
    "accessibility": 0.91,
    "bestPractices": 0.92,
    "seo": 0.97,
    "total": 317
  },
  "firstContentfulPaint": 2549.205,
  "firstMeaningfulPaint": 5951.103,
  "speedIndex": 5261.191601985193,
  "largestContentfulPaint": 8429.732999999998,
  "totalBlockingTime": 1000.5000000000018,
  "cumulativeLayoutShift": 0,
  "timeToInteractive": 13497.302000000001,
  "maxPotentialFirstInputDelay": 379,
  "timeToFirstByte": 25.53,
  "weight": {
    "summary": "70 requests • 3,534 KiB",
    "total": 3618494,
    "image": 1918413,
    "imageCount": 32,
    "script": 1350922,
    "scriptCount": 15,
    "document": 94335,
    "font": 67422,
    "fontCount": 6,
    "stylesheet": 153609,
    "stylesheetCount": 4,
    "thirdParty": 1029375,
    "thirdPartyCount": 29
  },
  "run": {
    "number": 2,
    "total": 3
  },
  "sidequests": {
    "-weight.total": 10,
    "+weight.total": 1,
    "-weight.document": 10,
    "+weight.document": 1,
    "-weight.script": 9,
    "+weight.script": 1,
    "-weight.image": 10,
    "+weight.image": 1,
    "-weight.font": 3,
    "+weight.font": 5,
    "+weight.fontCount": 1,
    "-timeToFirstByte": 7,
    "-totalBlockingTime": 8,
    "-largestContentfulPaint": 10
  },
  "axe": {
    "passes": 1351,
    "violations": 34
  }
}