{
  "url": "https://webdriver.io/",
  "requestedUrl": "https://webdriver.io/",
  "timestamp": 1656746336092,
  "ranks": {
    "hundos": 10,
    "performance": 10,
    "accessibility": 5,
    "cumulative": 10
  },
  "lighthouse": {
    "version": "9.6.3",
    "performance": 0.33,
    "accessibility": 0.91,
    "bestPractices": 0.92,
    "seo": 0.97,
    "total": 313
  },
  "firstContentfulPaint": 2958.361,
  "firstMeaningfulPaint": 6638.165999999999,
  "speedIndex": 4921.268183568738,
  "largestContentfulPaint": 7746.658499999999,
  "totalBlockingTime": 1371.4520000000002,
  "cumulativeLayoutShift": 0,
  "timeToInteractive": 13760.777500000002,
  "maxPotentialFirstInputDelay": 437,
  "timeToFirstByte": 13.466999999999999,
  "weight": {
    "summary": "68 requests • 2,140 KiB",
    "total": 2191546,
    "image": 537482,
    "imageCount": 30,
    "script": 1315646,
    "scriptCount": 14,
    "document": 93906,
    "font": 57228,
    "fontCount": 5,
    "stylesheet": 154247,
    "stylesheetCount": 5,
    "thirdParty": 1000365,
    "thirdPartyCount": 32
  },
  "run": {
    "number": 1,
    "total": 3
  },
  "axe": {
    "passes": 1065,
    "violations": 15
  }
}